toruscli/__init__.py
toruscli/app.py
toruscli/main.py
torus_cli-1.3.0.dist-info/LICENSE
torus_cli-1.3.0.dist-info/METADATA
torus_cli-1.3.0.dist-info/WHEEL
torus_cli-1.3.0.dist-info/top_level.txt
torus_cli-1.3.0.dist-info/RECORD
