Metadata-Version: 2.1
Name: torus-cli
Version: 1.3.0
Summary: Command line interface for torus-engine
Home-page: https://github.com/lucaalbinati/torus-cli
Author: Luca Albinati
Author-email: luca.albinati@gmail.com
License: UNKNOWN
Project-URL: Bug Tracker, https://github.com/lucaalbinati/torus-cli/issues
Platform: UNKNOWN
Classifier: Programming Language :: Python :: 3
Classifier: License :: OSI Approved :: MIT License
Classifier: Operating System :: OS Independent
Requires-Python: >=3.8
License-File: LICENSE
